pypungi/__init__.py
pypungi/app.py
pypungi/main.py
pypungi/models.py
pypungi/outlets.py
pypungi-0.11.16.dist-info/WHEEL
pypungi-0.11.16.dist-info/METADATA
pypungi-0.11.16.dist-info/RECORD
