Metadata-Version: 2.1
Name: pypungi
Version: 0.11.16
Summary: Helper tool
Home-page: https://github.com/jjotterson
License: UNKNOWN
Author: James Otterson
Author-email: jjotterson@gmail.com
Requires-Dist: statsmodels
Requires-Dist: zerorpc
